difftlk/__init__.py
difftlk-0.0.1.dist-info/METADATA
difftlk-0.0.1.dist-info/WHEEL
difftlk-0.0.1.dist-info/RECORD
